{
	"editor": {
		"allAngles": false,
		"entityTextureMode": false
	},
	"textureWidth": 16,
	"textureHeight": 16,
	"textureSizes": {
	},
	"textures": {
		"e7": "game:block/plant/crop/onion/e7",
		"s7": "game:block/plant/crop/onion/s7",
		"bulb": "game:block/plant/crop/onion/bulb"
	},
	"elements": [
		{
			"name": "origin",
			"from": [ 8.0, 0.0, 8.0 ], 
			"to": [ 8.0, 0.0, 8.0 ], 
			"rotationOrigin": [ 8.0, 0.0, 8.0 ],
			"faces": {
				"north": { "texture": "#null", "uv": [ 0.0, 0.0, 0.5, 0.5 ], "enabled": false },
				"east": { "texture": "#null", "uv": [ 0.0, 0.0, 0.5, 0.5 ] },
				"south": { "texture": "#null", "uv": [ 0.0, 0.0, 0.5, 0.5 ] },
				"west": { "texture": "#null", "uv": [ 0.0, 0.0, 0.5, 0.5 ] },
				"up": { "texture": "#null", "uv": [ 0.0, 0.0, 0.5, 0.5 ] },
				"down": { "texture": "#null", "uv": [ 0.0, 0.0, 0.5, 0.5 ] }
			},
			"children": [
				{
					"name": "onion 1",
					"from": [ -4.79, 0.0, -4.34 ], 
					"to": [ -3.01, 1.335, -2.56 ], 
					"rotationOrigin": [ -3.895, 0.0, -3.45 ],
					"rotationY": 45.0,
					"faces": {
						"north": { "texture": "#bulb", "uv": [ 6.0, 6.0, 7.5, 7.0 ], "windMode": [0,0,0,0] },
						"east": { "texture": "#bulb", "uv": [ 11.0, 6.0, 12.5, 7.0 ], "windMode": [0,0,0,0] },
						"south": { "texture": "#bulb", "uv": [ 2.0, 6.0, 3.5, 7.0 ], "windMode": [0,0,0,0] },
						"west": { "texture": "#bulb", "uv": [ 0.0, 6.0, 1.5, 7.0 ], "windMode": [0,0,0,0] },
						"up": { "texture": "#bulb", "uv": [ 2.0, 4.0, 3.5, 5.5 ], "windMode": [0,0,0,0] },
						"down": { "texture": "#bulb", "uv": [ 4.0, 3.0, 5.5, 4.5 ], "enabled": false }
					},
					"children": [
						{
							"name": "onion 1 top",
							"from": [ 0.445, 1.335, 0.445 ], 
							"to": [ 1.335, 1.78, 1.335 ], 
							"faces": {
								"north": { "texture": "#bulb", "uv": [ 12.0, 6.0, 12.89, 6.445 ], "windMode": [0,0,0,0] },
								"east": { "texture": "#bulb", "uv": [ 5.0, 6.0, 5.89, 6.445 ], "windMode": [0,0,0,0] },
								"south": { "texture": "#bulb", "uv": [ 4.0, 4.0, 4.89, 4.445 ], "windMode": [0,0,0,0] },
								"west": { "texture": "#bulb", "uv": [ 3.0, 6.0, 3.89, 6.445 ], "windMode": [0,0,0,0] },
								"up": { "texture": "#bulb", "uv": [ 12.0, 5.0, 12.89, 5.89 ], "windMode": [0,0,0,0] },
								"down": { "texture": "#bulb", "uv": [ 9.0, 7.0, 9.89, 7.89 ], "enabled": false }
							}
						},
						{
							"name": "s 1",
							"from": [ -4.895, 0.0, 0.89 ], 
							"to": [ 6.675, 11.57, 0.89 ], 
							"shade": false,
							"renderPass": 2,
							"rotationOrigin": [ 0.89, 0.0, 0.89 ],
							"faces": {
								"north": { "texture": "#leaves-we-8", "uv": [ 0.0, 0.0, 11.57, 11.57 ], "enabled": false },
								"east": { "texture": "#null", "uv": [ 0.0, 0.0, 0.0, 11.57 ], "enabled": false },
								"south": { "texture": "#s7", "uv": [ 1.5, 3.0, 13.07, 14.57 ], "windMode": [0,0,2,2] },
								"west": { "texture": "#null", "uv": [ 0.0, 0.0, 0.0, 11.57 ], "enabled": false },
								"up": { "texture": "#null", "uv": [ 0.0, 0.0, 11.57, 0.0 ], "enabled": false },
								"down": { "texture": "#null", "uv": [ 0.0, 0.0, 11.57, 0.0 ], "enabled": false }
							}
						},
						{
							"name": "e 1",
							"from": [ 0.89, 0.0, -5.34 ], 
							"to": [ 0.89, 11.57, 6.23 ], 
							"shade": false,
							"renderPass": 2,
							"rotationOrigin": [ 0.89, 0.0, 0.89 ],
							"faces": {
								"north": { "texture": "#null", "uv": [ 0.0, 0.0, 0.0, 11.57 ], "enabled": false },
								"east": { "texture": "#e7", "uv": [ 1.5, 3.0, 13.07, 14.57 ], "windMode": [0,2,2,0] },
								"south": { "texture": "#null", "uv": [ 0.0, 0.0, 0.0, 11.57 ], "enabled": false },
								"west": { "texture": "#null", "uv": [ 0.0, 0.0, 11.57, 11.57 ], "enabled": false },
								"up": { "texture": "#null", "uv": [ 0.0, 0.0, 0.0, 11.57 ], "enabled": false },
								"down": { "texture": "#null", "uv": [ 0.0, 0.0, 0.0, 11.57 ], "enabled": false }
							}
						}
					]
				},
				{
					"name": "onion 2",
					"from": [ -1.335, 0.0, -4.895 ], 
					"to": [ 0.89, 1.335, -2.67 ], 
					"rotationOrigin": [ -0.445, 0.0, -4.005 ],
					"rotationY": -22.5,
					"faces": {
						"north": { "texture": "#bulb", "uv": [ 7.0, 10.0, 9.225, 11.335 ], "windMode": [0,0,0,0] },
						"east": { "texture": "#bulb", "uv": [ 5.0, 10.0, 7.225, 11.335 ], "windMode": [0,0,0,0] },
						"south": { "texture": "#bulb", "uv": [ 2.0, 10.0, 4.225, 11.335 ], "windMode": [0,0,0,0] },
						"west": { "texture": "#bulb", "uv": [ 11.0, 10.0, 13.225, 11.335 ], "windMode": [0,0,0,0] },
						"up": { "texture": "#bulb", "uv": [ 6.0, 8.0, 8.225, 10.225 ], "windMode": [0,0,0,0] },
						"down": { "texture": "#bulb", "uv": [ 4.0, 3.0, 6.225, 5.225 ], "enabled": false }
					},
					"children": [
						{
							"name": "onion 2 top",
							"from": [ 0.445, 1.335, 0.445 ], 
							"to": [ 1.78, 1.78, 1.78 ], 
							"faces": {
								"north": { "texture": "#bulb", "uv": [ 8.0, 9.0, 9.335, 9.445 ], "windMode": [0,0,0,0] },
								"east": { "texture": "#bulb", "uv": [ 5.0, 10.0, 6.335, 10.445 ], "windMode": [0,0,0,0] },
								"south": { "texture": "#bulb", "uv": [ 11.0, 9.0, 12.335, 9.445 ], "windMode": [0,0,0,0] },
								"west": { "texture": "#bulb", "uv": [ 1.0, 10.0, 2.335, 10.445 ], "windMode": [0,0,0,0] },
								"up": { "texture": "#bulb", "uv": [ 3.0, 8.0, 4.335, 9.335 ], "windMode": [0,0,0,0] },
								"down": { "texture": "#bulb", "uv": [ 9.0, 7.0, 10.335, 8.335 ], "enabled": false }
							}
						},
						{
							"name": "s 2",
							"from": [ -4.539, 0.0, 1.068 ], 
							"to": [ 7.031, 11.57, 1.068 ], 
							"shade": false,
							"renderPass": 2,
							"rotationOrigin": [ 1.691, 0.0, 1.513 ],
							"faces": {
								"north": { "texture": "#null", "uv": [ 0.0, 0.0, 11.57, 11.57 ], "enabled": false },
								"east": { "texture": "#null", "uv": [ 0.0, 0.0, 0.0, 11.57 ], "enabled": false },
								"south": { "texture": "#s7", "uv": [ 1.5, 3.0, 13.07, 14.57 ], "windMode": [0,0,2,2] },
								"west": { "texture": "#null", "uv": [ 0.0, 0.0, 0.0, 11.57 ], "enabled": false },
								"up": { "texture": "#null", "uv": [ 0.0, 0.0, 11.57, 0.0 ], "enabled": false },
								"down": { "texture": "#null", "uv": [ 0.0, 0.0, 11.57, 0.0 ], "enabled": false }
							}
						},
						{
							"name": "e 2",
							"from": [ 1.068, 0.0, -4.895 ], 
							"to": [ 1.068, 11.57, 6.675 ], 
							"shade": false,
							"renderPass": 2,
							"rotationOrigin": [ 1.513, 0.0, 1.335 ],
							"faces": {
								"north": { "texture": "#null", "uv": [ 0.0, 0.0, 0.0, 11.57 ], "enabled": false },
								"east": { "texture": "#e7", "uv": [ 1.5, 3.0, 13.07, 14.57 ], "windMode": [0,2,2,0] },
								"south": { "texture": "#null", "uv": [ 0.0, 0.0, 0.0, 11.57 ], "enabled": false },
								"west": { "texture": "#null", "uv": [ 0.0, 0.0, 11.57, 11.57 ], "enabled": false },
								"up": { "texture": "#null", "uv": [ 0.0, 0.0, 0.0, 11.57 ], "enabled": false },
								"down": { "texture": "#null", "uv": [ 0.0, 0.0, 0.0, 11.57 ], "enabled": false }
							}
						}
					]
				},
				{
					"name": "onion 3",
					"from": [ 4.45, 0.0, -4.79 ], 
					"to": [ 6.23, 1.335, -3.01 ], 
					"rotationOrigin": [ 5.34, 0.0, -3.895 ],
					"rotationY": 22.5,
					"faces": {
						"north": { "texture": "#bulb", "uv": [ 12.0, 14.0, 13.5, 15.0 ], "windMode": [0,0,0,0] },
						"east": { "texture": "#bulb", "uv": [ 1.0, 14.0, 2.5, 15.0 ], "windMode": [0,0,0,0] },
						"south": { "texture": "#bulb", "uv": [ 4.0, 14.0, 5.5, 15.0 ], "windMode": [0,0,0,0] },
						"west": { "texture": "#bulb", "uv": [ 0.0, 14.0, 1.5, 15.0 ], "windMode": [0,0,0,0] },
						"up": { "texture": "#bulb", "uv": [ 12.0, 12.0, 13.5, 13.5 ], "windMode": [0,0,0,0] },
						"down": { "texture": "#bulb", "uv": [ 4.0, 3.0, 5.5, 4.5 ], "enabled": false }
					},
					"children": [
						{
							"name": "onion 3 top",
							"from": [ 0.445, 1.335, 0.445 ], 
							"to": [ 1.335, 1.78, 1.335 ], 
							"faces": {
								"north": { "texture": "#bulb", "uv": [ 9.0, 13.0, 9.89, 13.445 ], "windMode": [0,0,0,0] },
								"east": { "texture": "#bulb", "uv": [ 8.0, 13.0, 8.89, 13.445 ], "windMode": [0,0,0,0] },
								"south": { "texture": "#bulb", "uv": [ 8.0, 12.0, 8.89, 12.445 ], "windMode": [0,0,0,0] },
								"west": { "texture": "#bulb", "uv": [ 10.0, 13.0, 10.89, 13.445 ], "windMode": [0,0,0,0] },
								"up": { "texture": "#bulb", "uv": [ 9.0, 13.0, 9.89, 13.89 ], "windMode": [0,0,0,0] },
								"down": { "texture": "#bulb", "uv": [ 9.0, 7.0, 9.89, 7.89 ], "enabled": false }
							}
						},
						{
							"name": "s 3",
							"from": [ -4.895, 0.0, 0.89 ], 
							"to": [ 6.675, 11.57, 0.89 ], 
							"shade": false,
							"renderPass": 2,
							"rotationOrigin": [ 0.89, 0.0, 0.89 ],
							"faces": {
								"north": { "texture": "#leaves-we-8", "uv": [ 0.0, 0.0, 11.57, 11.57 ], "enabled": false },
								"east": { "texture": "#null", "uv": [ 0.0, 0.0, 0.0, 11.57 ], "enabled": false },
								"south": { "texture": "#s7", "uv": [ 1.5, 3.0, 13.07, 14.57 ], "windMode": [0,0,2,2] },
								"west": { "texture": "#null", "uv": [ 0.0, 0.0, 0.0, 11.57 ], "enabled": false },
								"up": { "texture": "#null", "uv": [ 0.0, 0.0, 11.57, 0.0 ], "enabled": false },
								"down": { "texture": "#null", "uv": [ 0.0, 0.0, 11.57, 0.0 ], "enabled": false }
							}
						},
						{
							"name": "e 3",
							"from": [ 0.89, 0.0, -4.895 ], 
							"to": [ 0.89, 11.57, 6.675 ], 
							"shade": false,
							"renderPass": 2,
							"rotationOrigin": [ 0.89, 0.0, 0.89 ],
							"faces": {
								"north": { "texture": "#null", "uv": [ 0.0, 0.0, 0.0, 11.57 ], "enabled": false },
								"east": { "texture": "#e7", "uv": [ 1.5, 3.0, 13.07, 14.57 ], "windMode": [0,2,2,0] },
								"south": { "texture": "#null", "uv": [ 0.0, 0.0, 0.0, 11.57 ], "enabled": false },
								"west": { "texture": "#null", "uv": [ 0.0, 0.0, 11.57, 11.57 ], "enabled": false },
								"up": { "texture": "#null", "uv": [ 0.0, 0.0, 0.0, 11.57 ], "enabled": false },
								"down": { "texture": "#null", "uv": [ 0.0, 0.0, 0.0, 11.57 ], "enabled": false }
							}
						}
					]
				},
				{
					"name": "onion 4",
					"from": [ -4.45, 0.0, 2.67 ], 
					"to": [ -2.67, 1.335, 4.45 ], 
					"rotationOrigin": [ -3.56, 0.0, 3.56 ],
					"rotationY": 45.0,
					"faces": {
						"north": { "texture": "#bulb", "uv": [ 6.0, 2.0, 7.78, 3.335 ], "windMode": [0,0,0,0] },
						"east": { "texture": "#bulb", "uv": [ 4.0, 2.0, 5.78, 3.335 ], "windMode": [0,0,0,0] },
						"south": { "texture": "#bulb", "uv": [ 10.0, 2.0, 11.78, 3.335 ], "windMode": [0,0,0,0] },
						"west": { "texture": "#bulb", "uv": [ 13.0, 2.0, 14.78, 3.335 ], "windMode": [0,0,0,0] },
						"up": { "texture": "#bulb", "uv": [ 8.0, 0.0, 9.78, 1.78 ], "windMode": [0,0,0,0] },
						"down": { "texture": "#bulb", "uv": [ 4.0, 3.0, 5.78, 4.78 ], "enabled": false }
					},
					"children": [
						{
							"name": "onion 4 top",
							"from": [ 0.445, 1.335, 0.445 ], 
							"to": [ 1.335, 1.78, 1.335 ], 
							"faces": {
								"north": { "texture": "#bulb", "uv": [ 12.0, 2.0, 12.89, 2.445 ], "windMode": [0,0,0,0] },
								"east": { "texture": "#bulb", "uv": [ 3.0, 1.0, 3.89, 1.445 ], "windMode": [0,0,0,0] },
								"south": { "texture": "#bulb", "uv": [ 10.0, 3.0, 10.89, 3.445 ], "windMode": [0,0,0,0] },
								"west": { "texture": "#bulb", "uv": [ 7.0, 2.0, 7.89, 2.445 ], "windMode": [0,0,0,0] },
								"up": { "texture": "#bulb", "uv": [ 6.0, 0.0, 6.89, 0.89 ], "windMode": [0,0,0,0] },
								"down": { "texture": "#bulb", "uv": [ 9.0, 7.0, 9.89, 7.89 ], "enabled": false }
							}
						},
						{
							"name": "s 4",
							"from": [ -4.895, 0.0, 0.89 ], 
							"to": [ 6.675, 11.57, 0.89 ], 
							"shade": false,
							"renderPass": 2,
							"rotationOrigin": [ 0.89, 0.0, 0.89 ],
							"faces": {
								"north": { "texture": "#leaves-we-8", "uv": [ 0.0, 0.0, 11.57, 11.57 ], "enabled": false },
								"east": { "texture": "#null", "uv": [ 0.0, 0.0, 0.0, 11.57 ], "enabled": false },
								"south": { "texture": "#s7", "uv": [ 1.5, 3.0, 13.07, 14.57 ], "windMode": [0,0,2,2] },
								"west": { "texture": "#null", "uv": [ 0.0, 0.0, 0.0, 11.57 ], "enabled": false },
								"up": { "texture": "#null", "uv": [ 0.0, 0.0, 11.57, 0.0 ], "enabled": false },
								"down": { "texture": "#null", "uv": [ 0.0, 0.0, 11.57, 0.0 ], "enabled": false }
							}
						},
						{
							"name": "e 4",
							"from": [ 0.89, 0.0, -4.895 ], 
							"to": [ 0.89, 11.57, 6.675 ], 
							"shade": false,
							"renderPass": 2,
							"rotationOrigin": [ 0.89, 0.0, 0.89 ],
							"faces": {
								"north": { "texture": "#null", "uv": [ 0.0, 0.0, 0.0, 11.57 ], "enabled": false },
								"east": { "texture": "#e7", "uv": [ 1.5, 3.0, 13.07, 14.57 ], "windMode": [0,2,2,0] },
								"south": { "texture": "#null", "uv": [ 0.0, 0.0, 0.0, 11.57 ], "enabled": false },
								"west": { "texture": "#null", "uv": [ 0.0, 0.0, 11.57, 11.57 ], "enabled": false },
								"up": { "texture": "#null", "uv": [ 0.0, 0.0, 0.0, 11.57 ], "enabled": false },
								"down": { "texture": "#null", "uv": [ 0.0, 0.0, 0.0, 11.57 ], "enabled": false }
							}
						}
					]
				},
				{
					"name": "onion 5",
					"from": [ 0.0, 0.0, 2.225 ], 
					"to": [ 1.78, 0.89, 4.005 ], 
					"rotationOrigin": [ 0.89, 0.0, 3.115 ],
					"rotationY": 22.5,
					"faces": {
						"north": { "texture": "#bulb", "uv": [ 5.0, 6.0, 6.78, 6.89 ], "windMode": [0,0,0,0] },
						"east": { "texture": "#bulb", "uv": [ 11.0, 6.0, 12.78, 6.89 ], "windMode": [0,0,0,0] },
						"south": { "texture": "#bulb", "uv": [ 3.0, 6.0, 4.78, 6.89 ], "windMode": [0,0,0,0] },
						"west": { "texture": "#bulb", "uv": [ 11.0, 6.0, 12.78, 6.89 ], "windMode": [0,0,0,0] },
						"up": { "texture": "#bulb", "uv": [ 13.0, 4.0, 14.78, 5.78 ], "windMode": [0,0,0,0] },
						"down": { "texture": "#bulb", "uv": [ 4.0, 3.0, 5.78, 4.78 ], "enabled": false }
					},
					"children": [
						{
							"name": "onion 5 top",
							"from": [ 0.445, 0.89, 0.445 ], 
							"to": [ 1.335, 1.335, 1.335 ], 
							"faces": {
								"north": { "texture": "#bulb", "uv": [ 10.0, 6.0, 10.89, 6.445 ], "windMode": [0,0,0,0] },
								"east": { "texture": "#bulb", "uv": [ 6.0, 6.0, 6.89, 6.445 ], "windMode": [0,0,0,0] },
								"south": { "texture": "#bulb", "uv": [ 12.0, 5.0, 12.89, 5.445 ], "windMode": [0,0,0,0] },
								"west": { "texture": "#bulb", "uv": [ 6.0, 5.0, 6.89, 5.445 ], "windMode": [0,0,0,0] },
								"up": { "texture": "#bulb", "uv": [ 14.0, 5.0, 14.89, 5.89 ], "windMode": [0,0,0,0] },
								"down": { "texture": "#bulb", "uv": [ 9.0, 7.0, 9.89, 7.89 ], "enabled": false }
							}
						},
						{
							"name": "s 5",
							"from": [ -4.895, -0.89, 0.89 ], 
							"to": [ 6.675, 10.68, 0.89 ], 
							"shade": false,
							"renderPass": 2,
							"rotationOrigin": [ 0.89, -0.89, 0.89 ],
							"faces": {
								"north": { "texture": "#leaves-we-8", "uv": [ 0.0, 0.0, 11.57, 11.57 ], "enabled": false },
								"east": { "texture": "#null", "uv": [ 0.0, 0.0, 0.0, 11.57 ], "enabled": false },
								"south": { "texture": "#s7", "uv": [ 1.5, 3.0, 13.07, 14.57 ], "windMode": [0,0,2,2] },
								"west": { "texture": "#null", "uv": [ 0.0, 0.0, 0.0, 11.57 ], "enabled": false },
								"up": { "texture": "#null", "uv": [ 0.0, 0.0, 11.57, 0.0 ], "enabled": false },
								"down": { "texture": "#null", "uv": [ 0.0, 0.0, 11.57, 0.0 ], "enabled": false }
							}
						},
						{
							"name": "e 5",
							"from": [ 0.89, -0.89, -5.34 ], 
							"to": [ 0.89, 10.68, 6.23 ], 
							"shade": false,
							"renderPass": 2,
							"rotationOrigin": [ 0.89, -0.89, 0.445 ],
							"faces": {
								"north": { "texture": "#null", "uv": [ 0.0, 0.0, 0.0, 11.57 ], "enabled": false },
								"east": { "texture": "#e7", "uv": [ 1.5, 3.0, 13.07, 14.57 ], "windMode": [0,2,2,0] },
								"south": { "texture": "#null", "uv": [ 0.0, 0.0, 0.0, 11.57 ], "enabled": false },
								"west": { "texture": "#null", "uv": [ 0.0, 0.0, 11.57, 11.57 ], "enabled": false },
								"up": { "texture": "#null", "uv": [ 0.0, 0.0, 0.0, 11.57 ], "enabled": false },
								"down": { "texture": "#null", "uv": [ 0.0, 0.0, 0.0, 11.57 ], "enabled": false }
							}
						}
					]
				},
				{
					"name": "onion 6",
					"from": [ 3.56, 0.0, 2.12 ], 
					"to": [ 5.785, 1.335, 4.345 ], 
					"rotationOrigin": [ 4.45, 0.0, 3.005 ],
					"rotationY": -22.5,
					"faces": {
						"north": { "texture": "#bulb", "uv": [ 10.0, 2.0, 12.0, 3.0 ], "windMode": [0,0,0,0] },
						"east": { "texture": "#bulb", "uv": [ 6.0, 2.0, 8.0, 3.0 ], "windMode": [0,0,0,0] },
						"south": { "texture": "#bulb", "uv": [ 1.0, 2.0, 3.0, 3.0 ], "windMode": [0,0,0,0] },
						"west": { "texture": "#bulb", "uv": [ 13.0, 2.0, 15.0, 3.0 ], "windMode": [0,0,0,0] },
						"up": { "texture": "#bulb", "uv": [ 5.0, 0.0, 7.0, 2.0 ], "windMode": [0,0,0,0] },
						"down": { "texture": "#bulb", "uv": [ 4.0, 3.0, 6.0, 5.0 ], "enabled": false }
					},
					"children": [
						{
							"name": "onion 6 top",
							"from": [ 0.445, 1.335, 0.445 ], 
							"to": [ 1.78, 1.78, 1.78 ], 
							"faces": {
								"north": { "texture": "#bulb", "uv": [ 8.0, 1.0, 9.335, 1.445 ], "windMode": [0,0,0,0] },
								"east": { "texture": "#bulb", "uv": [ 10.0, 1.0, 11.335, 1.445 ], "windMode": [0,0,0,0] },
								"south": { "texture": "#bulb", "uv": [ 2.0, 1.0, 3.335, 1.445 ], "windMode": [0,0,0,0] },
								"west": { "texture": "#bulb", "uv": [ 14.0, 0.0, 15.335, 0.445 ], "windMode": [0,0,0,0] },
								"up": { "texture": "#bulb", "uv": [ 6.0, 0.0, 7.335, 1.335 ], "windMode": [0,0,0,0] },
								"down": { "texture": "#bulb", "uv": [ 9.0, 7.0, 10.335, 8.335 ], "enabled": false }
							}
						},
						{
							"name": "s 6",
							"from": [ -4.717, 0.0, 1.157 ], 
							"to": [ 6.853, 11.57, 1.157 ], 
							"shade": false,
							"renderPass": 2,
							"rotationOrigin": [ 1.068, 0.0, 1.157 ],
							"faces": {
								"north": { "texture": "#leaves-we-8", "uv": [ 0.0, 0.0, 11.57, 11.57 ], "enabled": false },
								"east": { "texture": "#null", "uv": [ 0.0, 0.0, 0.0, 11.57 ], "enabled": false },
								"south": { "texture": "#s7", "uv": [ 1.5, 3.0, 13.07, 14.57 ], "windMode": [0,0,2,2] },
								"west": { "texture": "#null", "uv": [ 0.0, 0.0, 0.0, 11.57 ], "enabled": false },
								"up": { "texture": "#null", "uv": [ 0.0, 0.0, 11.57, 0.0 ], "enabled": false },
								"down": { "texture": "#null", "uv": [ 0.0, 0.0, 11.57, 0.0 ], "enabled": false }
							}
						},
						{
							"name": "e 6",
							"from": [ 0.89, 0.0, -4.895 ], 
							"to": [ 0.89, 11.57, 6.675 ], 
							"shade": false,
							"renderPass": 2,
							"rotationOrigin": [ 0.89, 0.0, 0.89 ],
							"faces": {
								"north": { "texture": "#null", "uv": [ 0.0, 0.0, 0.0, 11.57 ], "enabled": false },
								"east": { "texture": "#e7", "uv": [ 1.5, 3.0, 13.07, 14.57 ], "windMode": [0,2,2,0] },
								"south": { "texture": "#null", "uv": [ 0.0, 0.0, 0.0, 11.57 ], "enabled": false },
								"west": { "texture": "#null", "uv": [ 0.0, 0.0, 11.57, 11.57 ], "enabled": false },
								"up": { "texture": "#null", "uv": [ 0.0, 0.0, 0.0, 11.57 ], "enabled": false },
								"down": { "texture": "#null", "uv": [ 0.0, 0.0, 0.0, 11.57 ], "enabled": false }
							}
						}
					]
				}
			]
		},
		{
			"name": "origin",
			"from": [ 24.0, 0.0, 8.0 ], 
			"to": [ 24.0, 0.0, 8.0 ], 
			"rotationOrigin": [ 24.0, 0.0, 8.0 ],
			"rotationY": -180.0,
			"faces": {
				"north": { "texture": "#null", "uv": [ 0.0, 0.0, 0.5, 0.5 ], "enabled": false },
				"east": { "texture": "#null", "uv": [ 0.0, 0.0, 0.5, 0.5 ] },
				"south": { "texture": "#null", "uv": [ 0.0, 0.0, 0.5, 0.5 ] },
				"west": { "texture": "#null", "uv": [ 0.0, 0.0, 0.5, 0.5 ] },
				"up": { "texture": "#null", "uv": [ 0.0, 0.0, 0.5, 0.5 ] },
				"down": { "texture": "#null", "uv": [ 0.0, 0.0, 0.5, 0.5 ] }
			},
			"children": [
				{
					"name": "onion 1",
					"from": [ -4.79, 0.0, -4.34 ], 
					"to": [ -3.01, 1.335, -2.56 ], 
					"rotationOrigin": [ -3.895, 0.0, -3.45 ],
					"rotationY": 45.0,
					"faces": {
						"north": { "texture": "#bulb", "uv": [ 6.0, 6.0, 7.5, 7.0 ], "windMode": [0,0,0,0] },
						"east": { "texture": "#bulb", "uv": [ 11.0, 6.0, 12.5, 7.0 ], "windMode": [0,0,0,0] },
						"south": { "texture": "#bulb", "uv": [ 2.0, 6.0, 3.5, 7.0 ], "windMode": [0,0,0,0] },
						"west": { "texture": "#bulb", "uv": [ 0.0, 6.0, 1.5, 7.0 ], "windMode": [0,0,0,0] },
						"up": { "texture": "#bulb", "uv": [ 2.0, 4.0, 3.5, 5.5 ], "windMode": [0,0,0,0] },
						"down": { "texture": "#bulb", "uv": [ 4.0, 3.0, 5.5, 4.5 ], "enabled": false }
					},
					"children": [
						{
							"name": "onion 1 top",
							"from": [ 0.445, 1.335, 0.445 ], 
							"to": [ 1.335, 1.78, 1.335 ], 
							"faces": {
								"north": { "texture": "#bulb", "uv": [ 12.0, 6.0, 12.89, 6.445 ], "windMode": [0,0,0,0] },
								"east": { "texture": "#bulb", "uv": [ 5.0, 6.0, 5.89, 6.445 ], "windMode": [0,0,0,0] },
								"south": { "texture": "#bulb", "uv": [ 4.0, 4.0, 4.89, 4.445 ], "windMode": [0,0,0,0] },
								"west": { "texture": "#bulb", "uv": [ 3.0, 6.0, 3.89, 6.445 ], "windMode": [0,0,0,0] },
								"up": { "texture": "#bulb", "uv": [ 12.0, 5.0, 12.89, 5.89 ], "windMode": [0,0,0,0] },
								"down": { "texture": "#bulb", "uv": [ 9.0, 7.0, 9.89, 7.89 ], "enabled": false }
							}
						},
						{
							"name": "s 1",
							"from": [ -4.895, 0.0, 0.89 ], 
							"to": [ 6.675, 11.57, 0.89 ], 
							"shade": false,
							"renderPass": 2,
							"rotationOrigin": [ 0.89, 0.0, 0.89 ],
							"faces": {
								"north": { "texture": "#leaves-we-8", "uv": [ 0.0, 0.0, 11.57, 11.57 ], "enabled": false },
								"east": { "texture": "#null", "uv": [ 0.0, 0.0, 0.0, 11.57 ], "enabled": false },
								"south": { "texture": "#s7", "uv": [ 1.5, 3.0, 13.07, 14.57 ], "windMode": [0,0,2,2] },
								"west": { "texture": "#null", "uv": [ 0.0, 0.0, 0.0, 11.57 ], "enabled": false },
								"up": { "texture": "#null", "uv": [ 0.0, 0.0, 11.57, 0.0 ], "enabled": false },
								"down": { "texture": "#null", "uv": [ 0.0, 0.0, 11.57, 0.0 ], "enabled": false }
							}
						},
						{
							"name": "e 1",
							"from": [ 0.89, 0.0, -5.34 ], 
							"to": [ 0.89, 11.57, 6.23 ], 
							"shade": false,
							"renderPass": 2,
							"rotationOrigin": [ 0.89, 0.0, 0.89 ],
							"faces": {
								"north": { "texture": "#null", "uv": [ 0.0, 0.0, 0.0, 11.57 ], "enabled": false },
								"east": { "texture": "#e7", "uv": [ 1.5, 3.0, 13.07, 14.57 ], "windMode": [0,2,2,0] },
								"south": { "texture": "#null", "uv": [ 0.0, 0.0, 0.0, 11.57 ], "enabled": false },
								"west": { "texture": "#null", "uv": [ 0.0, 0.0, 11.57, 11.57 ], "enabled": false },
								"up": { "texture": "#null", "uv": [ 0.0, 0.0, 0.0, 11.57 ], "enabled": false },
								"down": { "texture": "#null", "uv": [ 0.0, 0.0, 0.0, 11.57 ], "enabled": false }
							}
						}
					]
				},
				{
					"name": "onion 2",
					"from": [ -1.335, 0.0, -4.895 ], 
					"to": [ 0.89, 1.335, -2.67 ], 
					"rotationOrigin": [ -0.445, 0.0, -4.005 ],
					"rotationY": -22.5,
					"faces": {
						"north": { "texture": "#bulb", "uv": [ 7.0, 10.0, 9.225, 11.335 ], "windMode": [0,0,0,0] },
						"east": { "texture": "#bulb", "uv": [ 5.0, 10.0, 7.225, 11.335 ], "windMode": [0,0,0,0] },
						"south": { "texture": "#bulb", "uv": [ 2.0, 10.0, 4.225, 11.335 ], "windMode": [0,0,0,0] },
						"west": { "texture": "#bulb", "uv": [ 11.0, 10.0, 13.225, 11.335 ], "windMode": [0,0,0,0] },
						"up": { "texture": "#bulb", "uv": [ 6.0, 8.0, 8.225, 10.225 ], "windMode": [0,0,0,0] },
						"down": { "texture": "#bulb", "uv": [ 4.0, 3.0, 6.225, 5.225 ], "enabled": false }
					},
					"children": [
						{
							"name": "onion 2 top",
							"from": [ 0.445, 1.335, 0.445 ], 
							"to": [ 1.78, 1.78, 1.78 ], 
							"faces": {
								"north": { "texture": "#bulb", "uv": [ 8.0, 9.0, 9.335, 9.445 ], "windMode": [0,0,0,0] },
								"east": { "texture": "#bulb", "uv": [ 5.0, 10.0, 6.335, 10.445 ], "windMode": [0,0,0,0] },
								"south": { "texture": "#bulb", "uv": [ 11.0, 9.0, 12.335, 9.445 ], "windMode": [0,0,0,0] },
								"west": { "texture": "#bulb", "uv": [ 1.0, 10.0, 2.335, 10.445 ], "windMode": [0,0,0,0] },
								"up": { "texture": "#bulb", "uv": [ 3.0, 8.0, 4.335, 9.335 ], "windMode": [0,0,0,0] },
								"down": { "texture": "#bulb", "uv": [ 9.0, 7.0, 10.335, 8.335 ], "enabled": false }
							}
						},
						{
							"name": "s 2",
							"from": [ -4.539, 0.0, 1.068 ], 
							"to": [ 7.031, 11.57, 1.068 ], 
							"shade": false,
							"renderPass": 2,
							"rotationOrigin": [ 1.691, 0.0, 1.513 ],
							"faces": {
								"north": { "texture": "#null", "uv": [ 0.0, 0.0, 11.57, 11.57 ], "enabled": false },
								"east": { "texture": "#null", "uv": [ 0.0, 0.0, 0.0, 11.57 ], "enabled": false },
								"south": { "texture": "#s7", "uv": [ 1.5, 3.0, 13.07, 14.57 ], "windMode": [0,0,2,2] },
								"west": { "texture": "#null", "uv": [ 0.0, 0.0, 0.0, 11.57 ], "enabled": false },
								"up": { "texture": "#null", "uv": [ 0.0, 0.0, 11.57, 0.0 ], "enabled": false },
								"down": { "texture": "#null", "uv": [ 0.0, 0.0, 11.57, 0.0 ], "enabled": false }
							}
						},
						{
							"name": "e 2",
							"from": [ 1.068, 0.0, -4.895 ], 
							"to": [ 1.068, 11.57, 6.675 ], 
							"shade": false,
							"renderPass": 2,
							"rotationOrigin": [ 1.513, 0.0, 1.335 ],
							"faces": {
								"north": { "texture": "#null", "uv": [ 0.0, 0.0, 0.0, 11.57 ], "enabled": false },
								"east": { "texture": "#e7", "uv": [ 1.5, 3.0, 13.07, 14.57 ], "windMode": [0,2,2,0] },
								"south": { "texture": "#null", "uv": [ 0.0, 0.0, 0.0, 11.57 ], "enabled": false },
								"west": { "texture": "#null", "uv": [ 0.0, 0.0, 11.57, 11.57 ], "enabled": false },
								"up": { "texture": "#null", "uv": [ 0.0, 0.0, 0.0, 11.57 ], "enabled": false },
								"down": { "texture": "#null", "uv": [ 0.0, 0.0, 0.0, 11.57 ], "enabled": false }
							}
						}
					]
				},
				{
					"name": "onion 3",
					"from": [ 4.45, 0.0, -4.79 ], 
					"to": [ 6.23, 1.335, -3.01 ], 
					"rotationOrigin": [ 5.34, 0.0, -3.895 ],
					"rotationY": 22.5,
					"faces": {
						"north": { "texture": "#bulb", "uv": [ 12.0, 14.0, 13.5, 15.0 ], "windMode": [0,0,0,0] },
						"east": { "texture": "#bulb", "uv": [ 1.0, 14.0, 2.5, 15.0 ], "windMode": [0,0,0,0] },
						"south": { "texture": "#bulb", "uv": [ 4.0, 14.0, 5.5, 15.0 ], "windMode": [0,0,0,0] },
						"west": { "texture": "#bulb", "uv": [ 0.0, 14.0, 1.5, 15.0 ], "windMode": [0,0,0,0] },
						"up": { "texture": "#bulb", "uv": [ 12.0, 12.0, 13.5, 13.5 ], "windMode": [0,0,0,0] },
						"down": { "texture": "#bulb", "uv": [ 4.0, 3.0, 5.5, 4.5 ], "enabled": false }
					},
					"children": [
						{
							"name": "onion 3 top",
							"from": [ 0.445, 1.335, 0.445 ], 
							"to": [ 1.335, 1.78, 1.335 ], 
							"faces": {
								"north": { "texture": "#bulb", "uv": [ 9.0, 13.0, 9.89, 13.445 ], "windMode": [0,0,0,0] },
								"east": { "texture": "#bulb", "uv": [ 8.0, 13.0, 8.89, 13.445 ], "windMode": [0,0,0,0] },
								"south": { "texture": "#bulb", "uv": [ 8.0, 12.0, 8.89, 12.445 ], "windMode": [0,0,0,0] },
								"west": { "texture": "#bulb", "uv": [ 10.0, 13.0, 10.89, 13.445 ], "windMode": [0,0,0,0] },
								"up": { "texture": "#bulb", "uv": [ 9.0, 13.0, 9.89, 13.89 ], "windMode": [0,0,0,0] },
								"down": { "texture": "#bulb", "uv": [ 9.0, 7.0, 9.89, 7.89 ], "enabled": false }
							}
						},
						{
							"name": "s 3",
							"from": [ -4.895, 0.0, 0.89 ], 
							"to": [ 6.675, 11.57, 0.89 ], 
							"shade": false,
							"renderPass": 2,
							"rotationOrigin": [ 0.89, 0.0, 0.89 ],
							"faces": {
								"north": { "texture": "#leaves-we-8", "uv": [ 0.0, 0.0, 11.57, 11.57 ], "enabled": false },
								"east": { "texture": "#null", "uv": [ 0.0, 0.0, 0.0, 11.57 ], "enabled": false },
								"south": { "texture": "#s7", "uv": [ 1.5, 3.0, 13.07, 14.57 ], "windMode": [0,0,2,2] },
								"west": { "texture": "#null", "uv": [ 0.0, 0.0, 0.0, 11.57 ], "enabled": false },
								"up": { "texture": "#null", "uv": [ 0.0, 0.0, 11.57, 0.0 ], "enabled": false },
								"down": { "texture": "#null", "uv": [ 0.0, 0.0, 11.57, 0.0 ], "enabled": false }
							}
						},
						{
							"name": "e 3",
							"from": [ 0.89, 0.0, -4.895 ], 
							"to": [ 0.89, 11.57, 6.675 ], 
							"shade": false,
							"renderPass": 2,
							"rotationOrigin": [ 0.89, 0.0, 0.89 ],
							"faces": {
								"north": { "texture": "#null", "uv": [ 0.0, 0.0, 0.0, 11.57 ], "enabled": false },
								"east": { "texture": "#e7", "uv": [ 1.5, 3.0, 13.07, 14.57 ], "windMode": [0,2,2,0] },
								"south": { "texture": "#null", "uv": [ 0.0, 0.0, 0.0, 11.57 ], "enabled": false },
								"west": { "texture": "#null", "uv": [ 0.0, 0.0, 11.57, 11.57 ], "enabled": false },
								"up": { "texture": "#null", "uv": [ 0.0, 0.0, 0.0, 11.57 ], "enabled": false },
								"down": { "texture": "#null", "uv": [ 0.0, 0.0, 0.0, 11.57 ], "enabled": false }
							}
						}
					]
				},
				{
					"name": "onion 4",
					"from": [ -4.45, 0.0, 2.67 ], 
					"to": [ -2.67, 1.335, 4.45 ], 
					"rotationOrigin": [ -3.56, 0.0, 3.56 ],
					"rotationY": 45.0,
					"faces": {
						"north": { "texture": "#bulb", "uv": [ 6.0, 2.0, 7.78, 3.335 ], "windMode": [0,0,0,0] },
						"east": { "texture": "#bulb", "uv": [ 4.0, 2.0, 5.78, 3.335 ], "windMode": [0,0,0,0] },
						"south": { "texture": "#bulb", "uv": [ 10.0, 2.0, 11.78, 3.335 ], "windMode": [0,0,0,0] },
						"west": { "texture": "#bulb", "uv": [ 13.0, 2.0, 14.78, 3.335 ], "windMode": [0,0,0,0] },
						"up": { "texture": "#bulb", "uv": [ 8.0, 0.0, 9.78, 1.78 ], "windMode": [0,0,0,0] },
						"down": { "texture": "#bulb", "uv": [ 4.0, 3.0, 5.78, 4.78 ], "enabled": false }
					},
					"children": [
						{
							"name": "onion 4 top",
							"from": [ 0.445, 1.335, 0.445 ], 
							"to": [ 1.335, 1.78, 1.335 ], 
							"faces": {
								"north": { "texture": "#bulb", "uv": [ 12.0, 2.0, 12.89, 2.445 ], "windMode": [0,0,0,0] },
								"east": { "texture": "#bulb", "uv": [ 3.0, 1.0, 3.89, 1.445 ], "windMode": [0,0,0,0] },
								"south": { "texture": "#bulb", "uv": [ 10.0, 3.0, 10.89, 3.445 ], "windMode": [0,0,0,0] },
								"west": { "texture": "#bulb", "uv": [ 7.0, 2.0, 7.89, 2.445 ], "windMode": [0,0,0,0] },
								"up": { "texture": "#bulb", "uv": [ 6.0, 0.0, 6.89, 0.89 ], "windMode": [0,0,0,0] },
								"down": { "texture": "#bulb", "uv": [ 9.0, 7.0, 9.89, 7.89 ], "enabled": false }
							}
						},
						{
							"name": "s 4",
							"from": [ -4.895, 0.0, 0.89 ], 
							"to": [ 6.675, 11.57, 0.89 ], 
							"shade": false,
							"renderPass": 2,
							"rotationOrigin": [ 0.89, 0.0, 0.89 ],
							"faces": {
								"north": { "texture": "#leaves-we-8", "uv": [ 0.0, 0.0, 11.57, 11.57 ], "enabled": false },
								"east": { "texture": "#null", "uv": [ 0.0, 0.0, 0.0, 11.57 ], "enabled": false },
								"south": { "texture": "#s7", "uv": [ 1.5, 3.0, 13.07, 14.57 ], "windMode": [0,0,2,2] },
								"west": { "texture": "#null", "uv": [ 0.0, 0.0, 0.0, 11.57 ], "enabled": false },
								"up": { "texture": "#null", "uv": [ 0.0, 0.0, 11.57, 0.0 ], "enabled": false },
								"down": { "texture": "#null", "uv": [ 0.0, 0.0, 11.57, 0.0 ], "enabled": false }
							}
						},
						{
							"name": "e 4",
							"from": [ 0.89, 0.0, -4.895 ], 
							"to": [ 0.89, 11.57, 6.675 ], 
							"shade": false,
							"renderPass": 2,
							"rotationOrigin": [ 0.89, 0.0, 0.89 ],
							"faces": {
								"north": { "texture": "#null", "uv": [ 0.0, 0.0, 0.0, 11.57 ], "enabled": false },
								"east": { "texture": "#e7", "uv": [ 1.5, 3.0, 13.07, 14.57 ], "windMode": [0,2,2,0] },
								"south": { "texture": "#null", "uv": [ 0.0, 0.0, 0.0, 11.57 ], "enabled": false },
								"west": { "texture": "#null", "uv": [ 0.0, 0.0, 11.57, 11.57 ], "enabled": false },
								"up": { "texture": "#null", "uv": [ 0.0, 0.0, 0.0, 11.57 ], "enabled": false },
								"down": { "texture": "#null", "uv": [ 0.0, 0.0, 0.0, 11.57 ], "enabled": false }
							}
						}
					]
				},
				{
					"name": "onion 5",
					"from": [ 0.0, 0.0, 2.225 ], 
					"to": [ 1.78, 0.89, 4.005 ], 
					"rotationOrigin": [ 0.89, 0.0, 3.115 ],
					"rotationY": 22.5,
					"faces": {
						"north": { "texture": "#bulb", "uv": [ 5.0, 6.0, 6.78, 6.89 ], "windMode": [0,0,0,0] },
						"east": { "texture": "#bulb", "uv": [ 11.0, 6.0, 12.78, 6.89 ], "windMode": [0,0,0,0] },
						"south": { "texture": "#bulb", "uv": [ 3.0, 6.0, 4.78, 6.89 ], "windMode": [0,0,0,0] },
						"west": { "texture": "#bulb", "uv": [ 11.0, 6.0, 12.78, 6.89 ], "windMode": [0,0,0,0] },
						"up": { "texture": "#bulb", "uv": [ 13.0, 4.0, 14.78, 5.78 ], "windMode": [0,0,0,0] },
						"down": { "texture": "#bulb", "uv": [ 4.0, 3.0, 5.78, 4.78 ], "enabled": false }
					},
					"children": [
						{
							"name": "onion 5 top",
							"from": [ 0.445, 0.89, 0.445 ], 
							"to": [ 1.335, 1.335, 1.335 ], 
							"faces": {
								"north": { "texture": "#bulb", "uv": [ 10.0, 6.0, 10.89, 6.445 ], "windMode": [0,0,0,0] },
								"east": { "texture": "#bulb", "uv": [ 6.0, 6.0, 6.89, 6.445 ], "windMode": [0,0,0,0] },
								"south": { "texture": "#bulb", "uv": [ 12.0, 5.0, 12.89, 5.445 ], "windMode": [0,0,0,0] },
								"west": { "texture": "#bulb", "uv": [ 6.0, 5.0, 6.89, 5.445 ], "windMode": [0,0,0,0] },
								"up": { "texture": "#bulb", "uv": [ 14.0, 5.0, 14.89, 5.89 ], "windMode": [0,0,0,0] },
								"down": { "texture": "#bulb", "uv": [ 9.0, 7.0, 9.89, 7.89 ], "enabled": false }
							}
						},
						{
							"name": "s 5",
							"from": [ -4.895, -0.89, 0.89 ], 
							"to": [ 6.675, 10.68, 0.89 ], 
							"shade": false,
							"renderPass": 2,
							"rotationOrigin": [ 0.89, -0.89, 0.89 ],
							"faces": {
								"north": { "texture": "#leaves-we-8", "uv": [ 0.0, 0.0, 11.57, 11.57 ], "enabled": false },
								"east": { "texture": "#null", "uv": [ 0.0, 0.0, 0.0, 11.57 ], "enabled": false },
								"south": { "texture": "#s7", "uv": [ 1.5, 3.0, 13.07, 14.57 ], "windMode": [0,0,2,2] },
								"west": { "texture": "#null", "uv": [ 0.0, 0.0, 0.0, 11.57 ], "enabled": false },
								"up": { "texture": "#null", "uv": [ 0.0, 0.0, 11.57, 0.0 ], "enabled": false },
								"down": { "texture": "#null", "uv": [ 0.0, 0.0, 11.57, 0.0 ], "enabled": false }
							}
						},
						{
							"name": "e 5",
							"from": [ 0.89, -0.89, -5.34 ], 
							"to": [ 0.89, 10.68, 6.23 ], 
							"shade": false,
							"renderPass": 2,
							"rotationOrigin": [ 0.89, -0.89, 0.445 ],
							"faces": {
								"north": { "texture": "#null", "uv": [ 0.0, 0.0, 0.0, 11.57 ], "enabled": false },
								"east": { "texture": "#e7", "uv": [ 1.5, 3.0, 13.07, 14.57 ], "windMode": [0,2,2,0] },
								"south": { "texture": "#null", "uv": [ 0.0, 0.0, 0.0, 11.57 ], "enabled": false },
								"west": { "texture": "#null", "uv": [ 0.0, 0.0, 11.57, 11.57 ], "enabled": false },
								"up": { "texture": "#null", "uv": [ 0.0, 0.0, 0.0, 11.57 ], "enabled": false },
								"down": { "texture": "#null", "uv": [ 0.0, 0.0, 0.0, 11.57 ], "enabled": false }
							}
						}
					]
				},
				{
					"name": "onion 6",
					"from": [ 3.56, 0.0, 2.12 ], 
					"to": [ 5.785, 1.335, 4.345 ], 
					"rotationOrigin": [ 4.45, 0.0, 3.005 ],
					"rotationY": -22.5,
					"faces": {
						"north": { "texture": "#bulb", "uv": [ 10.0, 2.0, 12.0, 3.0 ], "windMode": [0,0,0,0] },
						"east": { "texture": "#bulb", "uv": [ 6.0, 2.0, 8.0, 3.0 ], "windMode": [0,0,0,0] },
						"south": { "texture": "#bulb", "uv": [ 1.0, 2.0, 3.0, 3.0 ], "windMode": [0,0,0,0] },
						"west": { "texture": "#bulb", "uv": [ 13.0, 2.0, 15.0, 3.0 ], "windMode": [0,0,0,0] },
						"up": { "texture": "#bulb", "uv": [ 5.0, 0.0, 7.0, 2.0 ], "windMode": [0,0,0,0] },
						"down": { "texture": "#bulb", "uv": [ 4.0, 3.0, 6.0, 5.0 ], "enabled": false }
					},
					"children": [
						{
							"name": "onion 6 top",
							"from": [ 0.445, 1.335, 0.445 ], 
							"to": [ 1.78, 1.78, 1.78 ], 
							"faces": {
								"north": { "texture": "#bulb", "uv": [ 8.0, 1.0, 9.335, 1.445 ], "windMode": [0,0,0,0] },
								"east": { "texture": "#bulb", "uv": [ 10.0, 1.0, 11.335, 1.445 ], "windMode": [0,0,0,0] },
								"south": { "texture": "#bulb", "uv": [ 2.0, 1.0, 3.335, 1.445 ], "windMode": [0,0,0,0] },
								"west": { "texture": "#bulb", "uv": [ 14.0, 0.0, 15.335, 0.445 ], "windMode": [0,0,0,0] },
								"up": { "texture": "#bulb", "uv": [ 6.0, 0.0, 7.335, 1.335 ], "windMode": [0,0,0,0] },
								"down": { "texture": "#bulb", "uv": [ 9.0, 7.0, 10.335, 8.335 ], "enabled": false }
							}
						},
						{
							"name": "s 6",
							"from": [ -4.717, 0.0, 1.157 ], 
							"to": [ 6.853, 11.57, 1.157 ], 
							"shade": false,
							"renderPass": 2,
							"rotationOrigin": [ 1.068, 0.0, 1.157 ],
							"faces": {
								"north": { "texture": "#leaves-we-8", "uv": [ 0.0, 0.0, 11.57, 11.57 ], "enabled": false },
								"east": { "texture": "#null", "uv": [ 0.0, 0.0, 0.0, 11.57 ], "enabled": false },
								"south": { "texture": "#s7", "uv": [ 1.5, 3.0, 13.07, 14.57 ], "windMode": [0,0,2,2] },
								"west": { "texture": "#null", "uv": [ 0.0, 0.0, 0.0, 11.57 ], "enabled": false },
								"up": { "texture": "#null", "uv": [ 0.0, 0.0, 11.57, 0.0 ], "enabled": false },
								"down": { "texture": "#null", "uv": [ 0.0, 0.0, 11.57, 0.0 ], "enabled": false }
							}
						},
						{
							"name": "e 6",
							"from": [ 0.89, 0.0, -4.895 ], 
							"to": [ 0.89, 11.57, 6.675 ], 
							"shade": false,
							"renderPass": 2,
							"rotationOrigin": [ 0.89, 0.0, 0.89 ],
							"faces": {
								"north": { "texture": "#null", "uv": [ 0.0, 0.0, 0.0, 11.57 ], "enabled": false },
								"east": { "texture": "#e7", "uv": [ 1.5, 3.0, 13.07, 14.57 ], "windMode": [0,2,2,0] },
								"south": { "texture": "#null", "uv": [ 0.0, 0.0, 0.0, 11.57 ], "enabled": false },
								"west": { "texture": "#null", "uv": [ 0.0, 0.0, 11.57, 11.57 ], "enabled": false },
								"up": { "texture": "#null", "uv": [ 0.0, 0.0, 0.0, 11.57 ], "enabled": false },
								"down": { "texture": "#null", "uv": [ 0.0, 0.0, 0.0, 11.57 ], "enabled": false }
							}
						}
					]
				}
			]
		}
	]}